{"api-reference_authentication_readme.md":"2e5d038e","user-account_get-users.md":"088b325c","user-account_update-account.md":"1a731423","api-reference_data-types_readme.md":"bf407050","database_delete-records.md":"9cacc5e6","authentication_signup-confirmation.md":"701bd796","realtime_group.md":"1bd8ebea","user-account_change-password.md":"69b90c11","api-reference_email_readme.md":"27dfe331","api-reference_realtime_readme.md":"8415cad8","database_index.md":"0de5a85f","database_referencing.md":"58110fa9","database_subscription.md":"0342652a","database_table-info.md":"fe37229a","database_tags.md":"bf4c9d49","email_email-templates.md":"2486f954","email_newsletters.md":"47bc4f37","introduction_getting-started.md":"2ab2845a","introduction_working-with-forms.md":"0ce951ea","realtime_connecting.md":"65a5e989","realtime_post.md":"d5e4fa1e","security_api-bridge.md":"65158435","security_security-settings.md":"51b8bdf5","database_update-record.md":"89d2a051","database_fetch.md":"f42a21c5","database_create.md":"b95831e0","hosting_hosting.md":"92921cc6","authentication_create-account.md":"51db171d","authentication_login-logout.md":"31db110c","api-reference_user_readme.md":"9a19e627","api-reference_database_readme.md":"c039786b","index.md":"0b3c96e2","user-account_email-verification.md":"9d4b74da","user-account_full-example.md":"73ec777a","database_access-restrictions.md":"26e7e452","database_handling-files.md":"389b8c02","user-account_disable-recover-account.md":"8b740519","authentication_forgot-password.md":"f4048d15","authentication_full-example.md":"fb51c910","full-example_photo-sharing-app.md":"61fcafbd"}
